mcp_sleep/__init__.py
mcp_sleep/__main__.py
mcp_sleep/server.py
mcp_sleep/sleep/__init__.py
mcp_sleep/sleep/client.py
mcp_sleep/sleep/config.py
mcp_sleep/sleep/wait.py
mcp_sleep-0.1.1.dist-info/METADATA
mcp_sleep-0.1.1.dist-info/WHEEL
mcp_sleep-0.1.1.dist-info/entry_points.txt
mcp_sleep-0.1.1.dist-info/licenses/LICENSE
mcp_sleep-0.1.1.dist-info/RECORD
