Metadata-Version: 2.4
Name: mcp-sleep
Version: 0.1.1
Summary: Tool that allows you to wait a certain time to continue the execution of an agent.
Author-email: StylusFrost <pm.diaz.pena@gmail.com>
License-File: LICENSE
Requires-Python: >=3.13
Requires-Dist: click>=8.1.8
Requires-Dist: dotenv>=0.9.9
Requires-Dist: mcp>=1.5.0
